milla_tdf/__init__.py
milla_tdf/auth_token/fiin_trade/__init__.py
milla_tdf/config/__init__.py
milla_tdf/crawler/abstract.py
milla_tdf/crawler/error_codes/__init__.py
milla_tdf/crawler/fiin_com_financial_data/__init__.py
milla_tdf/crawler/fiin_stock_price_data/__init__.py
milla_tdf/crawler/fiin_symbols_info/__init__.py
milla_tdf/data_model/abstract.py
milla_tdf/data_model/com_financial_data/__init__.py
milla_tdf/data_model/stock_price_data/__init__.py
milla_tdf/data_model/symbols_info/__init__.py
milla_tdf/field_mapping/__init__.py
milla_tdf/logger/__init__.py
milla_tdf/storage/abstract.py
milla_tdf/storage/local/__init__.py
milla_tdf/transform/error_codes/__init__.py
milla_tdf/transform/trading_date_financial_data/__init__.py
milla_tdf-0.1.1.dist-info/METADATA
milla_tdf-0.1.1.dist-info/WHEEL
milla_tdf-0.1.1.dist-info/top_level.txt
milla_tdf-0.1.1.dist-info/RECORD
